DiceLib/__init__.py
DiceLib/die.py
DiceLib/exceptions.py
DiceLib/rolls.py
DiceLib-0.2.0.dist-info/LICENSE
DiceLib-0.2.0.dist-info/METADATA
DiceLib-0.2.0.dist-info/WHEEL
DiceLib-0.2.0.dist-info/top_level.txt
DiceLib-0.2.0.dist-info/RECORD
