Metadata-Version: 2.1
Name: DiceLib
Version: 0.2.0
Summary: A dice-rolling library for RPGs.
Home-page: https://github.com/rolecraft/DiceLib
Author: CMSteffen
Author-email: cmsteffen@protonmail.com
License: MIT
Platform: UNKNOWN
Classifier: License :: OSI Approved :: MIT License
Classifier: Programming Language :: Python :: 3
Classifier: Programming Language :: Python :: 3.7
